.gitignore
LICENSE
MANIFEST.in
README.txt
setup.py
cs/__init__.py
cs.plone5.tinymcepatch.egg-info/PKG-INFO
cs.plone5.tinymcepatch.egg-info/SOURCES.txt
cs.plone5.tinymcepatch.egg-info/dependency_links.txt
cs.plone5.tinymcepatch.egg-info/entry_points.txt
cs.plone5.tinymcepatch.egg-info/namespace_packages.txt
cs.plone5.tinymcepatch.egg-info/not-zip-safe
cs.plone5.tinymcepatch.egg-info/requires.txt
cs.plone5.tinymcepatch.egg-info/top_level.txt
cs/plone5/__init__.py
cs/plone5/tinymcepatch/__init__.py
cs/plone5/tinymcepatch/configure.zcml
cs/plone5/tinymcepatch/patches.py
cs/plone5/tinymcepatch/tests.py
docs/HISTORY.txt
docs/INSTALL.txt
docs/LICENSE.GPL
docs/LICENSE.txt