Metadata-Version: 1.1
Name: cs.plone5.tinymcepatch
Version: 1.0.3
Summary: Patch to make TinyMCE Upload work in Plone <= 5.0.6 with p.a.multilingual
Home-page: https://github.com/codesyntax/cs.plone5.tinymcepatch
Author: Mikel Larreategi
Author-email: mlarreategi@codesyntax.com
License: GPL
Platform: UNKNOWN
Classifier: Framework :: Plone
Classifier: Framework :: Plone :: 5.0
Classifier: Programming Language :: Python
